AUTHORS.md
CONTRIBUTORS.md
LICENCE
MANIFEST.in
README.md
requirements.txt
setup.cfg
setup.py
data/21071600.pos
data/230923.gpx
data/XYZBRAVOSANSFIDOUTEST.txt
data/c2c-1028091.dat
data/demicercle.csv
data/gcp.txt
data/hybridation_gnss_camera.dat
data/hybridation_gnss_camera.pos
data/imu_opk_Vincennes1909121306.txt
data/log_gnss_12032021-12-19-29.pos
data/log_gnss_17042021-13-07-14.ubx
data/log_gnss_22032021-15-20-23.pos
data/mobile.pos
data/psr.dat
data/psr_all.dat
data/rawGps1Data.pos
data/raw_gps.pos
data/raw_gps_ECEF.pos
data/rover1.pos
data/rover2.pos
data/rtk_l93.txt
data/satellites_no_errors.txt
data/satellites_no_erros.txt
data/sol.pos
data/test_2sats.dat
data/trace0.gps
data/trace1.dat
data/trace10_mm.dat
data/trace9.gps
data/ublox_exp.pos
data/asc/8961191.csv
data/asc/8961191.qmd
data/asc/8961191_v2.csv
data/asc/8961191_v3.csv
data/asc/RGEALTI_0930_6415_LAMB93_IGN69.asc
data/asc/mnt_XYZBRAVOSANSFIDOUTEST_2.asc
data/asc/mnt_XYZBRAVOSANSFIDOUTEST_2.prj
data/asc/test.asc
data/csv/22245.csv
data/gpx/20180131T121746.gpx
data/gpx/456.gpx
data/gpx/457.gpx
data/gpx/903313.gpx
data/gpx/activity_5807084803.gpx
data/gpx/utgtrack-22245.gpx
data/gpx/utgtrack-22245_light.gpx
data/gpx/vincennes.gpx
data/gpx/geo/5_56.gpx
data/gpx/geo/5_85.gpx
data/lacet/3troncons.csv
data/lacet/ecrins.csv
data/lacet/sentier.csv
data/mopsi/1412412627743_3857.csv
data/mopsi/1412412627743_3857.qmd
data/mopsi/wgs84/1296044888896
data/mopsi/wgs84/1296056764388
data/mopsi/wgs84/1296059175859
data/mopsi/wgs84/1317719870259
data/mopsi/wgs84/1317811076881
data/mopsi/wgs84/1317887241981
data/mopsi/wgs84/1326875947364
data/mopsi/wgs84/1326876906653
data/mopsi/wgs84/1326877249248
data/mopsi/wgs84/1326877679263
data/mopsi/wgs84/1326878428305
data/mopsi/wgs84/1326878921902
data/mopsi/wgs84/1327478450896
data/mopsi/wgs84/1327574182972
data/mopsi/wgs84/1327574464296
data/mopsi/wgs84/1327834421003
data/mopsi/wgs84/1329687780034
data/mopsi/wgs84/1329765531089
data/mopsi/wgs84/1329914184453
tracklib.egg-info/PKG-INFO
tracklib.egg-info/SOURCES.txt
tracklib.egg-info/dependency_links.txt
tracklib.egg-info/requires.txt
tracklib.egg-info/top_level.txt
