Metadata-Version: 2.1
Name: tracklib
Version: 0.7.3
Summary: tracklib library provides a variety of tools, operators and functions to manipulate GPS trajectories
Home-page: https://github.com/umrlastig/tracklib
Author: Yann Méneroux, Marie-Dominique Van Damme
Author-email: todo@ign.fr
License: Cecill-C
Download-URL: https://github.com/umrlastig/tracklib/archive/refs/tags/v0.7.3.tar.gz
Keywords: GPS track,Python library,Map-matching,Trajectory fusion,Synthetic trajectory,Segmenting GPS tracks,Summarizing GPS tracks,Stop positions,Kalman filter
Platform: UNKNOWN
Classifier: Development Status :: 4 - Beta
Classifier: Intended Audience :: Developers
Classifier: Programming Language :: Python :: 3.8
Classifier: Programming Language :: Python :: 3.10
Classifier: Programming Language :: Python :: 3.12
Requires-Python: >=3.8
Provides-Extra: dev
Provides-Extra: doc
License-File: LICENCE
License-File: AUTHORS.md
